heraw/__init__.py
heraw/client.py
heraw/exceptions.py
heraw/py.typed
heraw/types/__init__.py
heraw/types/cast.py
heraw/types/custom_field.py
heraw/types/entity.py
heraw/types/file.py
heraw/types/folder.py
heraw/types/project.py
heraw/types/search.py
heraw/types/subtitle.py
heraw/types/task.py
heraw/types/workspace.py
heraw-0.1.0.dist-info/licenses/LICENSE
heraw-0.1.0.dist-info/METADATA
heraw-0.1.0.dist-info/WHEEL
heraw-0.1.0.dist-info/top_level.txt
heraw-0.1.0.dist-info/RECORD
