Metadata-Version: 2.4
Name: heraw
Version: 0.1.0
Summary: Python SDK for the heraw API
Author: heraw Team
License-Expression: MIT
Project-URL: Homepage, https://github.com/heraw/python-heraw
Project-URL: Bug Tracker, https://github.com/heraw/python-heraw/issues
Project-URL: Documentation, https://app.heraw.com/docs/api
Classifier: Programming Language :: Python :: 3
Classifier: Operating System :: OS Independent
Classifier: Development Status :: 4 - Beta
Classifier: Intended Audience :: Developers
Classifier: Topic :: Software Development :: Libraries :: Python Modules
Requires-Python: >=3.7
License-File: LICENSE
Requires-Dist: requests>=2.25.0
Dynamic: license-file
